barcode/DejaVuSansMono.ttf
barcode/__init__.py
barcode/base.py
barcode/codex.py
barcode/ean.py
barcode/errors.py
barcode/isxn.py
barcode/pybarcode.py
barcode/upc.py
barcode/writer.py
barcode/charsets/__init__.py
barcode/charsets/code128.py
barcode/charsets/code39.py
barcode/charsets/ean.py
reBarcode-0.1.0.dist-info/DESCRIPTION.rst
reBarcode-0.1.0.dist-info/METADATA
reBarcode-0.1.0.dist-info/RECORD
reBarcode-0.1.0.dist-info/WHEEL
reBarcode-0.1.0.dist-info/entry_points.txt
reBarcode-0.1.0.dist-info/metadata.json
reBarcode-0.1.0.dist-info/top_level.txt
