Metadata-Version: 2.0
Name: reBarcode
Version: 0.1.0
Summary: Create standard barcodes with Python. No external modules needed (optional PIL support included).
Home-page: https://github.com/trobertsca/reBarcode
Author: Thorsten Weimann, Alexander Shorin, Timothy Roberts
Author-email: timothyroberts.ca@gmail.com
License: MIT
Platform: UNKNOWN
Classifier: Development Status :: 4 - Beta
Classifier: Environment :: Console
Classifier: Intended Audience :: Developers
Classifier: License :: OSI Approved :: MIT License
Classifier: Operating System :: OS Independent
Classifier: Programming Language :: Python
Classifier: Programming Language :: Python :: 2
Classifier: Programming Language :: Python :: 2.6
Classifier: Programming Language :: Python :: 2.7
Classifier: Programming Language :: Python :: 3
Classifier: Programming Language :: Python :: 3.3
Classifier: Programming Language :: Python :: 3.4
Classifier: Topic :: Software Development :: Libraries :: Python Modules
Classifier: Topic :: Multimedia :: Graphics
